{
  "ComponentIndexes": {
    "Header": 4,
    "Header_1": 3,
    "Header_3": 3,
    "Navbar": 3,
    "navbar_2": 2,
    "navbar_3": 2
  },
  "ControlUniqueGuids": {},
  "ControlUniqueIds": {
    "Apellido _DataCard1": 30,
    "App": 1,
    "Button1": 14,
    "Button3": 8,
    "Container13": 11,
    "Container14": 12,
    "Container2": 6,
    "Container6": 16,
    "Container9": 17,
    "Crear": 55,
    "DataCardKey1": 26,
    "DataCardKey2": 31,
    "DataCardKey3": 36,
    "DataCardKey5": 46,
    "DataCardKey6": 51,
    "DataCardKey7": 81,
    "DataCardValue1": 27,
    "DataCardValue2": 32,
    "DataCardValue3": 37,
    "DataCardValue5": 47,
    "DataCardValue6": 52,
    "DataCardValue7": 82,
    "Edad_DataCard1": 35,
    "ErrorMessage1": 28,
    "ErrorMessage2": 33,
    "ErrorMessage3": 38,
    "ErrorMessage5": 48,
    "ErrorMessage6": 53,
    "ErrorMessage7": 83,
    "Gallery4": 9,
    "galleryTemplate2": 62,
    "galleryTemplate4": 10,
    "Header": 15,
    "Header_1": 59,
    "Header_3": 71,
    "Home": 22,
    "Host": 3,
    "Icon1": 19,
    "Image1": 74,
    "Image3": 13,
    "Image6": 21,
    "Ingreso_Al_Trabajo_DataCard1": 45,
    "Label2": 18,
    "Label3": 20,
    "Linkedin_DataCard1": 50,
    "Navbar": 4,
    "navbar_2": 57,
    "navbar_3": 73,
    "navbar-Container": 5,
    "navbar-Logo_1": 7,
    "NewPerson": 23,
    "NewPerson_Header": 58,
    "NewPerson_Insert": 24,
    "NewPerson_Navbar": 56,
    "NextArrow1": 77,
    "Nombre_DataCard1": 25,
    "Perfil_DataCard2": 80,
    "Rectangle1": 79,
    "Separator1": 78,
    "StarVisible1": 29,
    "StarVisible2": 34,
    "StarVisible3": 39,
    "StarVisible5": 49,
    "StarVisible6": 54,
    "StarVisible7": 84,
    "Subtitle1": 76,
    "Title1": 75,
    "User": 60,
    "User_Gallery": 61,
    "User_Header": 70,
    "User_Navbar": 72
  },
  "FunctionParamsInvariantScripts": {},
  "FunctionParamsInvariantScriptsOnInstances": {},
  "HeaderLastSavedDateTimeUTC": "09/28/2024 04:03:52",
  "IsLegacyComponentAllowGlobalScopeCase": false,
  "LocalConnectionIDReferences": {
    "c4d280a6-f339-4b5a-8ada-48648695d3df": "\"/providers/microsoft.powerapps/apis/shared_sharepointonline/connections/6d1b6f2543ca4c7ea53455d3b472ff8c\""
  },
  "LocalDatabaseReferencesAsEmpty": true,
  "LocalResourceFileNames": {
    "A": "9a7f73d0-5039-4c58-bfd3-3b9edb8a9965.png"
  },
  "LocalResourceRootPaths": {
    "A": "https://docserverpwaprodwus.blob.core.windows.net/9f2b8a60-3848-4e5d-8d1d-08ddeb668dd6-1/resource/Assets0Images09a7f73d0-5039-4c58-bfd3-3b9edb8a9965.png?skoid=58690ece-ec83-4ce2-9ce8-883d4d6a54ee&sktid=975f013f-7f24-47e8-a7d3-abc4752bf346&skt=2024-09-28T03%3A49%3A39Z&ske=2024-09-29T04%3A04%3A39Z&sks=b&skv=2023-01-03&sv=2023-01-03&spr=https&se=2024-09-29T04%3A04%3A39Z&sr=b&sp=r&sig=eVZlOvH9r%2BKrJNINBKQeAobT9r5bbCXwEHlB08Y92yc%3D"
  },
  "OldLogoFileName": "na3dvabo.jpg",
  "OrderComponentMetadata": {
    "2554a52b66044696bc114d0c8815b9bd": 1,
    "87a76ae00310482bb4d7975c739ab8d3": 0
  },
  "OrderComponentTemplate": {
    "2554a52b66044696bc114d0c8815b9bd": 1,
    "87a76ae00310482bb4d7975c739ab8d3": 0
  },
  "OrderDataSource": {
    "ComboBoxSample": 2,
    "CustomGallerySample": 0,
    "Lista Andrés Clavijo": 1
  },
  "OrderGroupControls": {},
  "OrderPcfTemplate": {},
  "OrderTemplate": {},
  "OrderXMLTemplate": {
    "button": 5,
    "combobox": 4,
    "datepicker": 3,
    "form": 0,
    "gallery": 8,
    "groupContainer": 6,
    "icon": 9,
    "image": 7,
    "label": 1,
    "rectangle": 10,
    "text": 2
  },
  "OverridablePropertiesEntry": {
    "Apellido _DataCard1": {},
    "App": {},
    "Button1": {},
    "Button3": {},
    "Container13": {},
    "Container14": {},
    "Container2": {},
    "Container6": {},
    "Container9": {},
    "Crear": {},
    "DataCardKey1": {},
    "DataCardKey2": {},
    "DataCardKey3": {},
    "DataCardKey5": {},
    "DataCardKey6": {},
    "DataCardKey7": {},
    "DataCardValue1": {},
    "DataCardValue2": {},
    "DataCardValue3": {},
    "DataCardValue5": {},
    "DataCardValue6": {},
    "DataCardValue7": {},
    "Edad_DataCard1": {},
    "ErrorMessage1": {},
    "ErrorMessage2": {},
    "ErrorMessage3": {},
    "ErrorMessage5": {},
    "ErrorMessage6": {},
    "ErrorMessage7": {},
    "Gallery4": {},
    "galleryTemplate2": {},
    "galleryTemplate4": {},
    "Header": {},
    "Header_1": {},
    "Header_3": {},
    "Home": {},
    "Host": {},
    "Icon1": {},
    "Image1": {},
    "Image3": {},
    "Image6": {},
    "Ingreso_Al_Trabajo_DataCard1": {},
    "Label2": {},
    "Label3": {},
    "Linkedin_DataCard1": {},
    "Navbar": {},
    "navbar_2": {},
    "navbar_3": {},
    "navbar-Container": {},
    "navbar-Logo_1": {},
    "NewPerson": {},
    "NewPerson_Header": {},
    "NewPerson_Insert": {},
    "NewPerson_Navbar": {},
    "NextArrow1": {},
    "Nombre_DataCard1": {},
    "Perfil_DataCard2": {},
    "Rectangle1": {},
    "Separator1": {},
    "StarVisible1": {},
    "StarVisible2": {},
    "StarVisible3": {},
    "StarVisible5": {},
    "StarVisible6": {},
    "StarVisible7": {},
    "Subtitle1": {},
    "Title1": {},
    "User": {},
    "User_Gallery": {},
    "User_Header": {},
    "User_Navbar": {}
  },
  "PCFDynamicSchemaForIRRetrievalEntry": {},
  "PCFTemplateEntry": {},
  "PublishOrderIndices": {
    "Apellido _DataCard1": 0,
    "App": 0,
    "Button1": 446,
    "Button3": 440,
    "Container13": 443,
    "Container14": 444,
    "Container2": 438,
    "Container6": 448,
    "Container9": 449,
    "Crear": 0,
    "DataCardKey1": 0,
    "DataCardKey2": 0,
    "DataCardKey3": 0,
    "DataCardKey5": 0,
    "DataCardKey6": 0,
    "DataCardKey7": 0,
    "DataCardValue1": 0,
    "DataCardValue2": 0,
    "DataCardValue3": 0,
    "DataCardValue5": 0,
    "DataCardValue6": 0,
    "DataCardValue7": 0,
    "Edad_DataCard1": 0,
    "ErrorMessage1": 0,
    "ErrorMessage2": 0,
    "ErrorMessage3": 0,
    "ErrorMessage5": 0,
    "ErrorMessage6": 0,
    "ErrorMessage7": 0,
    "Gallery4": 441,
    "galleryTemplate2": 0,
    "galleryTemplate4": 442,
    "Header": 0,
    "Header_1": 0,
    "Header_3": 0,
    "Home": 0,
    "Host": 0,
    "Icon1": 451,
    "Image1": 0,
    "Image3": 445,
    "Image6": 453,
    "Ingreso_Al_Trabajo_DataCard1": 0,
    "Label2": 450,
    "Label3": 452,
    "Linkedin_DataCard1": 0,
    "Navbar": 0,
    "navbar_2": 0,
    "navbar_3": 0,
    "navbar-Container": 437,
    "navbar-Logo_1": 439,
    "NewPerson": 0,
    "NewPerson_Header": 0,
    "NewPerson_Insert": 0,
    "NewPerson_Navbar": 0,
    "NextArrow1": 0,
    "Nombre_DataCard1": 0,
    "Perfil_DataCard2": 0,
    "Rectangle1": 0,
    "Separator1": 0,
    "StarVisible1": 0,
    "StarVisible2": 0,
    "StarVisible3": 0,
    "StarVisible5": 0,
    "StarVisible6": 0,
    "StarVisible7": 0,
    "Subtitle1": 0,
    "Title1": 0,
    "User": 0,
    "User_Gallery": 0,
    "User_Header": 0,
    "User_Navbar": 0
  },
  "ResourcesJsonIndices": {
    "Image-A": 0,
    "Image-SampleImage": 1
  },
  "RuleScreenIdWithoutScreen": {},
  "TemplateVersions": {},
  "VolatileProperties": {
    "AnalysisLoadTime": 0.6130586,
    "ControlCount": {
      "2554a52b66044696bc114d0c8815b9bd": 3,
      "87a76ae00310482bb4d7975c739ab8d3": 3,
      "button": 3,
      "combobox": 1,
      "datepicker": 1,
      "form": 1,
      "gallery": 2,
      "galleryTemplate": 2,
      "groupContainer": 10,
      "icon": 2,
      "image": 4,
      "label": 23,
      "rectangle": 2,
      "screen": 3,
      "text": 4,
      "typedDataCard": 6
    },
    "DeserializationLoadTime": 2.1919146
  },
  "WasLocalDatabaseReferencesEmpty": true
}